<?xml version="1.0" encoding="utf-8" ?><dwsync><file name="bground.gif" server="ashleywing.net/public_html/cottageindustryfilms/CIF_newer/" local="3422714576" remote="12013311872" /><file name="bground.png" server="ashleywing.net/public_html/cottageindustryfilms/CIF_newer/" local="3422775158" remote="12013311092" /><file name="cif_watermark.png" server="ashleywing.net/public_html/cottageindustryfilms/CIF_newer/" local="3422775455" remote="12013311092" /><file name="divider" server="ashleywing.net/public_html/cottageindustryfilms/CIF_newer/" local="3422716992" remote="12013311092" /><file name="divider.png" server="ashleywing.net/public_html/cottageindustryfilms/CIF_newer/" local="3422717003" remote="12013311092" /><file name="footer_gradient.png" server="ashleywing.net/public_html/cottageindustryfilms/CIF_newer/" local="3422776749" remote="12013311092" /><file name="logo.png" server="ashleywing.net/public_html/cottageindustryfilms/CIF_newer/" local="3422715350" remote="12013311092" /><file name="main_gradient.png" server="ashleywing.net/public_html/cottageindustryfilms/CIF_newer/" local="3423403313" remote="12013311932" /><file name="main_gradient_watermark.png" server="ashleywing.net/public_html/cottageindustryfilms/CIF_newer/" local="3422775980" remote="12013311932" /><file name="news_border.png" server="ashleywing.net/public_html/cottageindustryfilms/CIF_newer/" local="3422781741" remote="12013311092" /><file name="clash.gif" server="ashleywing.net/public_html/cottageindustryfilms/CIF_newer/" local="3341692800" remote="12013311932" /><file name="menuToggle.png" server="ashleywing.net/public_html/cottageindustryfilms/CIF_newer/" local="3423301362" remote="12013311092" /><file name=".DS_Store" server="ashleywing.net/public_html/cottageindustryfilms/CIF_newer/" local="3423249598" remote="12013311092" /><file name="news_border.png" server="ashleywing.net/public_html/cottageindustryfilms/" local="3422781741" remote="12013315592" /><file name="cif_watermark.png" server="ashleywing.net/public_html/cottageindustryfilms/" local="3422775455" remote="12013315592" /><file name="divider" server="ashleywing.net/public_html/cottageindustryfilms/" local="3422716992" remote="12013315592" /><file name="footer_gradient.png" server="ashleywing.net/public_html/cottageindustryfilms/" local="3422776749" remote="12013315592" /><file name="menuToggle.png" server="ashleywing.net/public_html/cottageindustryfilms/" local="3423301362" remote="12013315592" /><file name=".DS_Store" server="ashleywing.net/public_html/cottageindustryfilms/" local="3423249598" remote="12013315592" /><file name="logo.png" server="ashleywing.net/public_html/cottageindustryfilms/" local="3422715350" remote="12013315592" /><file name="bground.png" server="ashleywing.net/public_html/cottageindustryfilms/" local="3422775158" remote="12013315592" /><file name="divider.png" server="ashleywing.net/public_html/cottageindustryfilms/" local="3422717003" remote="12013315592" /><file name="bground.gif" server="ashleywing.net/public_html/cottageindustryfilms/" local="3422714576" remote="12013316372" /><file name="main_gradient_watermark.png" server="ashleywing.net/public_html/cottageindustryfilms/" local="3422775980" remote="12013316432" /><file name="clash.gif" server="ashleywing.net/public_html/cottageindustryfilms/" local="3341692800" remote="12013316432" /><file name="main_gradient.png" server="ashleywing.net/public_html/cottageindustryfilms/" local="3423403313" remote="12013316432" /><file name="imageLink.jpg" server="ashleywing.net/public_html/cottageindustryfilms/" local="3423411459" remote="16308284568" /><file name="apple-touch-icon.png" server="ashleywing.net/public_html/cottageindustryfilms/" local="3423415046" remote="16308288228" /><file name="news_border.png" server="hadrian.lunariffic.com/public_html/" local="3425802824" remote="12015705092" /><file name="cif_watermark.png" server="hadrian.lunariffic.com/public_html/" local="3425802824" remote="12015705092" /><file name="divider" server="hadrian.lunariffic.com/public_html/" local="3425802824" remote="12015705092" /><file name="imageLink.jpg" server="hadrian.lunariffic.com/public_html/" local="3425802825" remote="12015705092" /><file name="footer_gradient.png" server="hadrian.lunariffic.com/public_html/" local="3425802826" remote="12015705092" /><file name="menuToggle.png" server="hadrian.lunariffic.com/public_html/" local="3425802826" remote="12015705092" /><file name=".DS_Store" server="hadrian.lunariffic.com/public_html/" local="3425802826" remote="12015705092" /><file name="logo.png" server="hadrian.lunariffic.com/public_html/" local="3425802827" remote="12015705092" /><file name="bground.png" server="hadrian.lunariffic.com/public_html/" local="3425802827" remote="12015705092" /><file name="divider.png" server="hadrian.lunariffic.com/public_html/" local="3425802827" remote="12015705092" /><file name="bground.gif" server="hadrian.lunariffic.com/public_html/" local="3425802876" remote="12015705932" /><file name="main_gradient_watermark.png" server="hadrian.lunariffic.com/public_html/" local="3425802894" remote="12015705992" /><file name="apple-touch-icon.png" server="hadrian.lunariffic.com/public_html/" local="3425802896" remote="12015705992" /><file name="clash.gif" server="hadrian.lunariffic.com/public_html/" local="3425802897" remote="12015705992" /><file name="main_gradient.png" server="hadrian.lunariffic.com/public_html/" local="3425802897" remote="12015705992" /><file name="dayReturnPoster_thumb.jpg" server="hadrian.lunariffic.com/public_html/" local="3429990000" remote="16314891888" /><file name="dayReturnPoster_Facebook.jpg" server="hadrian.lunariffic.com/public_html/" local="3429990000" remote="16314891888" /></dwsync>